{
  "annotations": [],
  "body": "<div><span style=\"color: var(--text); font-size: 0.95em;\">撞击地球后，神灵陷入半休眠状态。祂的意识沉入一场漫长而纷乱的梦境——七十亿人类的记忆如潮水般涌入，彼此交叠、碰撞、融合。祂不再只是祂，而是一场浩瀚灵魂的合奏。</span></div>\n两亿年的时光悄然流逝。祂没有干涉这片大地的任何发展，任由一切按照因果的法则自生自灭。当祂终于从沉睡中苏醒，眼前已是一片全然陌生的世界——新大陆上早已涌现出无数奇异的魔法生物，它们在这片天地间繁衍生息。<div><br></div><div><span style=\"font-size: 15.2px; white-space-collapse: collapse; background-color: rgba(200, 146, 42, 0.08);\">【白鲸】苏醒的神灵赋予了自己一个名字。</span>\n\n白鲸静静凝视这一切，沉思良久。终于，祂使用两亿年间积蓄的大部分力量，将一些体型庞大，性格暴虐的魔物化作人形，给予智慧。随后将剩余的力量凭空构建出新的人类，并从意识里剥离出灵魂，放入其中。耗尽魔力的白鲸便再次陷入了漫长的沉睡。</div>",
  "created": "2026-04-02",
  "tags": [
    [
      "设定",
      "人物"
    ]
  ],
  "title": "白鲸",
  "uid": "shenling"
}